CHANGES.rst
CONTRIBUTORS.rst
MANIFEST.in
README.rst
setup.cfg
setup.py
docs/LICENSE.GPL
docs/LICENSE.txt
src/interlegis/__init__.py
src/interlegis.portalmodelo.migrator.egg-info/PKG-INFO
src/interlegis.portalmodelo.migrator.egg-info/SOURCES.txt
src/interlegis.portalmodelo.migrator.egg-info/dependency_links.txt
src/interlegis.portalmodelo.migrator.egg-info/entry_points.txt
src/interlegis.portalmodelo.migrator.egg-info/namespace_packages.txt
src/interlegis.portalmodelo.migrator.egg-info/not-zip-safe
src/interlegis.portalmodelo.migrator.egg-info/requires.txt
src/interlegis.portalmodelo.migrator.egg-info/top_level.txt
src/interlegis/portalmodelo/__init__.py
src/interlegis/portalmodelo/migrator/__init__.py
src/interlegis/portalmodelo/migrator/configure.zcml
src/interlegis/portalmodelo/migrator/forms.py
src/interlegis/portalmodelo/migrator/pm2_migration.py
src/interlegis/portalmodelo/migrator/portal_modelo_2.cfg
src/interlegis/portalmodelo/migrator/resilient_blueprints.py